matomerumi/__init__.py
matomerumi/__main__.py
matomerumi/matomerumi_lib/__init__.py
matomerumi/matomerumi_lib/matomerumi.py
matomerumi/matomerumi_lib/mmi_auto_styles.py
matomerumi/matomerumi_lib/mmi_config.py
matomerumi/matomerumi_lib/mmi_odtgenlib.py
matomerumi/matomerumi_lib/mmi_parser.py
matomerumi/matomerumi_lib/mmi_path_handler.py
matomerumi/matomerumi_lib/mmi_templates.py
matomeru_mi-2022.6.22.dist-info/LICENSE
matomeru_mi-2022.6.22.dist-info/METADATA
matomeru_mi-2022.6.22.dist-info/WHEEL
matomeru_mi-2022.6.22.dist-info/top_level.txt
matomeru_mi-2022.6.22.dist-info/RECORD
