Metadata-Version: 2.1
Name: matomeru-mi
Version: 2022.6.22
Summary: A Markdown-like markup language interpreter
Home-page: https://gitlab.com/Fe-Ti/matomeru-mi
Author: Fe-Ti
Author-email: btm.007@mail.ru
Project-URL: Bug Tracker, https://gitlab.com/Fe-Ti/matomeru-mi/issues
Project-URL: Documentation, https://fe-ti.gitlab.io/matomeru-mi/index.html
Classifier: Programming Language :: Python :: 3
Classifier: License :: OSI Approved :: BSD License
Classifier: Operating System :: OS Independent
Requires-Python: >=3.6
License-File: LICENSE
